odoo/addons/maintenance_equipment_contract/README.rst
odoo/addons/maintenance_equipment_contract/__init__.py
odoo/addons/maintenance_equipment_contract/__manifest__.py
odoo/addons/maintenance_equipment_contract/demo/maintenance_equipment_contract_demo.xml
odoo/addons/maintenance_equipment_contract/i18n/es.po
odoo/addons/maintenance_equipment_contract/i18n/it.po
odoo/addons/maintenance_equipment_contract/i18n/maintenance_equipment_contract.pot
odoo/addons/maintenance_equipment_contract/i18n/pt_BR.po
odoo/addons/maintenance_equipment_contract/models/__init__.py
odoo/addons/maintenance_equipment_contract/models/contract_contract.py
odoo/addons/maintenance_equipment_contract/models/maintenance_equipment.py
odoo/addons/maintenance_equipment_contract/readme/CONTRIBUTORS.md
odoo/addons/maintenance_equipment_contract/readme/DESCRIPTION.md
odoo/addons/maintenance_equipment_contract/static/description/icon.png
odoo/addons/maintenance_equipment_contract/static/description/index.html
odoo/addons/maintenance_equipment_contract/tests/__init__.py
odoo/addons/maintenance_equipment_contract/tests/test_equipment_contract.py
odoo/addons/maintenance_equipment_contract/views/contract_contract.xml
odoo/addons/maintenance_equipment_contract/views/maintenance_equipment.xml
odoo_addon_maintenance_equipment_contract-18.0.1.0.0.2.dist-info/METADATA
odoo_addon_maintenance_equipment_contract-18.0.1.0.0.2.dist-info/WHEEL
odoo_addon_maintenance_equipment_contract-18.0.1.0.0.2.dist-info/top_level.txt
odoo_addon_maintenance_equipment_contract-18.0.1.0.0.2.dist-info/RECORD
