Metadata-Version: 2.1
Name: odoo-addon-maintenance_equipment_contract
Version: 18.0.1.0.0.2
Requires-Python: >=3.10
Requires-Dist: odoo-addon-base_maintenance==18.0.*
Requires-Dist: odoo-addon-contract==18.0.*
Requires-Dist: odoo==18.0.*
Summary: Manage equipment contracts
Home-page: https://github.com/OCA/maintenance
License: AGPL-3
Author: Creu Blanca,Odoo Community Association (OCA)
Author-email: support@odoo-community.org
Classifier: Programming Language :: Python
Classifier: Framework :: Odoo
Classifier: Framework :: Odoo :: 18.0
Classifier: License :: OSI Approved :: GNU Affero General Public License v3
